{
  "spot": "Mah\u00f3n/Menorca Aeropuerto",
  "coordinates": {
    "latitude": 39.86,
    "longitude": 4.22
  },
  "country_code": "ES",
  "is_weather_station": true,
  "month": [
    1,
    1,
    1,
    1,
    1,
    1,
    1,
    1,
    1,
    1,
    1,
    1,
    1,
    1,
    1,
    1,
    1,
    1,
    1,
    1,
    1,
    1,
    1,
    1,
    1,
    1,
    1,
    1,
    1,
    1,
    1,
    1,
    1,
    1,
    1,
    1,
    1,
    1,
    1,
    1,
    1,
    1,
    1,
    1,
    1,
    1,
    1,
    1,
    1,
    1,
    1,
    1,
    1,
    1,
    1,
    1,
    1,
    1,
    1,
    1,
    1,
    1,
    1,
    1,
    1,
    1,
    1,
    1,
    1,
    1,
    1,
    1,
    1,
    1,
    1,
    1,
    1,
    1,
    1,
    1
  ],
  "day": [
    13,
    13,
    13,
    13,
    13,
    13,
    13,
    13,
    14,
    14,
    14,
    14,
    14,
    14,
    14,
    14,
    15,
    15,
    15,
    15,
    15,
    15,
    15,
    15,
    16,
    16,
    16,
    16,
    16,
    16,
    16,
    16,
    17,
    17,
    17,
    17,
    17,
    17,
    17,
    17,
    18,
    18,
    18,
    18,
    18,
    18,
    18,
    18,
    19,
    19,
    19,
    19,
    19,
    19,
    19,
    19,
    20,
    20,
    20,
    20,
    20,
    20,
    20,
    20,
    21,
    21,
    21,
    21,
    21,
    21,
    21,
    21,
    22,
    22,
    22,
    22,
    22,
    22,
    22,
    22
  ],
  "weekday": [
    "Wednesday",
    "Wednesday",
    "Wednesday",
    "Wednesday",
    "Wednesday",
    "Wednesday",
    "Wednesday",
    "Wednesday",
    "Thursday",
    "Thursday",
    "Thursday",
    "Thursday",
    "Thursday",
    "Thursday",
    "Thursday",
    "Thursday",
    "Friday",
    "Friday",
    "Friday",
    "Friday",
    "Friday",
    "Friday",
    "Friday",
    "Friday",
    "Saturday",
    "Saturday",
    "Saturday",
    "Saturday",
    "Saturday",
    "Saturday",
    "Saturday",
    "Saturday",
    "Sunday",
    "Sunday",
    "Sunday",
    "Sunday",
    "Sunday",
    "Sunday",
    "Sunday",
    "Sunday",
    "Monday",
    "Monday",
    "Monday",
    "Monday",
    "Monday",
    "Monday",
    "Monday",
    "Monday",
    "Tuesday",
    "Tuesday",
    "Tuesday",
    "Tuesday",
    "Tuesday",
    "Tuesday",
    "Tuesday",
    "Tuesday",
    "Wednesday",
    "Wednesday",
    "Wednesday",
    "Wednesday",
    "Wednesday",
    "Wednesday",
    "Wednesday",
    "Wednesday",
    "Thursday",
    "Thursday",
    "Thursday",
    "Thursday",
    "Thursday",
    "Thursday",
    "Thursday",
    "Thursday",
    "Friday",
    "Friday",
    "Friday",
    "Friday",
    "Friday",
    "Friday",
    "Friday",
    "Friday"
  ],
  "hour": [
    6,
    8,
    10,
    12,
    14,
    16,
    18,
    20,
    6,
    8,
    10,
    12,
    14,
    16,
    18,
    20,
    1,
    4,
    7,
    10,
    13,
    16,
    19,
    22,
    1,
    4,
    7,
    10,
    13,
    16,
    19,
    22,
    1,
    4,
    7,
    10,
    13,
    16,
    19,
    22,
    1,
    4,
    7,
    10,
    13,
    16,
    19,
    22,
    1,
    4,
    7,
    10,
    13,
    16,
    19,
    22,
    1,
    4,
    7,
    10,
    13,
    16,
    19,
    22,
    1,
    4,
    7,
    10,
    13,
    16,
    19,
    22,
    1,
    4,
    7,
    10,
    13,
    16,
    19
  ],
  "current_wind": 6,
  "current_wind_direction": 300,
  "wind_speed": [
    12,
    12,
    13,
    14,
    14,
    11,
    8,
    7,
    10,
    10,
    8,
    6,
    6,
    4,
    3,
    2,
    10,
    14,
    10,
    4,
    5,
    6,
    11,
    20,
    22,
    29,
    26,
    23,
    19,
    20,
    11,
    12,
    16,
    12,
    8,
    10,
    11,
    7,
    9,
    4,
    9,
    8,
    6,
    4,
    8,
    9,
    5,
    4,
    6,
    9,
    13,
    14,
    14,
    14,
    16,
    17,
    19,
    19,
    19,
    20,
    20,
    20,
    20,
    21,
    20,
    20,
    22,
    20,
    24,
    25,
    17,
    21,
    18,
    12,
    9,
    8,
    4,
    14,
    15
  ],
  "wind_gusts": [
    14,
    14,
    14,
    14,
    16,
    17,
    14,
    12,
    16,
    16,
    8,
    6,
    8,
    6,
    4,
    6,
    11,
    16,
    11,
    5,
    6,
    8,
    13,
    22,
    25,
    33,
    32,
    27,
    23,
    25,
    16,
    16,
    20,
    15,
    10,
    13,
    13,
    9,
    10,
    8,
    9,
    8,
    6,
    7,
    9,
    10,
    7,
    6,
    9,
    11,
    16,
    17,
    17,
    18,
    23,
    26,
    28,
    28,
    28,
    28,
    27,
    27,
    28,
    29,
    29,
    29,
    32,
    29,
    33,
    36,
    31,
    34,
    25,
    13,
    9,
    8,
    6,
    17,
    19
  ],
  "wind_direction": [
    270,
    277,
    278,
    280,
    290,
    301,
    314,
    316,
    280,
    299,
    312,
    296,
    293,
    317,
    22,
    12,
    292,
    281,
    298,
    325,
    274,
    282,
    35,
    12,
    7,
    358,
    6,
    9,
    10,
    16,
    339,
    279,
    266,
    273,
    267,
    255,
    255,
    257,
    13,
    38,
    34,
    19,
    6,
    184,
    240,
    272,
    276,
    285,
    239,
    220,
    203,
    201,
    204,
    209,
    212,
    216,
    225,
    228,
    241,
    236,
    230,
    230,
    227,
    228,
    231,
    222,
    238,
    234,
    232,
    232,
    238,
    250,
    287,
    19,
    18,
    36,
    152,
    298,
    296
  ],
  "wave_height": [
    0.9,
    0.9,
    0.8,
    0.9,
    0.9,
    0.9,
    0.8,
    0.6,
    0.6,
    0.6,
    0.5,
    0.5,
    0.5,
    0.5,
    0.5,
    0.5,
    0.7,
    0.8,
    0.7,
    0.7,
    0.7,
    0.8,
    0.8,
    0.0,
    0,
    0,
    0,
    0,
    0,
    0,
    0,
    0,
    0,
    0,
    0,
    0,
    0,
    0,
    0,
    0,
    0,
    0,
    0,
    0,
    0,
    0,
    0,
    0,
    0,
    0,
    0,
    0,
    0,
    0,
    0,
    0,
    0,
    0,
    0,
    0,
    0,
    0,
    0,
    0,
    0,
    0,
    0,
    0,
    0,
    0,
    0,
    0,
    0,
    0,
    0,
    0,
    0,
    0,
    0,
    0
  ],
  "wave_period": [
    4.0,
    4.0,
    4.0,
    4.0,
    5.0,
    5.0,
    5.0,
    5.0,
    4.0,
    4.0,
    4.0,
    4.0,
    4.0,
    4.0,
    4.0,
    4.0,
    4.0,
    4.0,
    6.0,
    6.0,
    6.0,
    6.0,
    6.0,
    0.0,
    0,
    0,
    0,
    0,
    0,
    0,
    0,
    0,
    0,
    0,
    0,
    0,
    0,
    0,
    0,
    0,
    0,
    0,
    0,
    0,
    0,
    0,
    0,
    0,
    0,
    0,
    0,
    0,
    0,
    0,
    0,
    0,
    0,
    0,
    0,
    0,
    0,
    0,
    0,
    0,
    0,
    0,
    0,
    0,
    0,
    0,
    0,
    0,
    0,
    0,
    0,
    0,
    0,
    0,
    0,
    0
  ],
  "wave_direction": [
    282,
    277,
    274,
    284,
    284,
    281,
    278,
    269,
    275,
    279,
    280,
    283,
    285,
    286,
    288,
    287,
    274,
    278,
    279,
    288,
    299,
    323,
    358,
    0,
    0,
    0,
    0,
    0,
    0,
    0,
    0,
    0,
    0,
    0,
    0,
    0,
    0,
    0,
    0,
    0,
    0,
    0,
    0,
    0,
    0,
    0,
    0,
    0,
    0,
    0,
    0,
    0,
    0,
    0,
    0,
    0,
    0,
    0,
    0,
    0,
    0,
    0,
    0,
    0,
    0,
    0,
    0,
    0,
    0,
    0,
    0,
    0,
    0,
    0,
    0,
    0,
    0,
    0,
    0,
    0
  ],
  "weather_icon": [
    "moon.fill",
    "moon.fill",
    "sun.max.fill",
    "sun.max.fill",
    "sun.max.fill",
    "sun.max.fill",
    "moon.fill",
    "moon.fill",
    "moon.fill",
    "moon.fill",
    "cloud.sun.fill",
    "cloud.sun.fill",
    "cloud.sun.fill",
    "cloud.sun.fill",
    "cloud.moon.fill",
    "cloud.moon.fill",
    "cloud.moon.fill",
    "cloud.moon.fill",
    "cloud.moon.fill",
    "cloud.sun.fill",
    "cloud.sun.fill",
    "cloud.sun.fill",
    "cloud.moon.fill",
    "cloud.moon.fill",
    "cloud.fill",
    "cloud.fill",
    "cloud.fill",
    "cloud.sun.fill",
    "cloud.sun.fill",
    "sun.max.fill",
    "moon.fill",
    "cloud.moon.fill",
    "moon.fill",
    "moon.fill",
    "moon.fill",
    "sun.max.fill",
    "sun.max.fill",
    "sun.max.fill",
    "cloud.moon.fill",
    "cloud.fill",
    "cloud.fill",
    "cloud.moon.fill",
    "cloud.moon.fill",
    "cloud.sun.fill",
    "cloud.sun.fill",
    "sun.max.fill",
    "moon.fill",
    "moon.fill",
    "moon.fill",
    "moon.fill",
    "cloud.moon.fill",
    "cloud.fill",
    "cloud.fill",
    "cloud.fill",
    "cloud.moon.fill",
    "cloud.moon.fill",
    "cloud.fill",
    "cloud.moon.fill",
    "cloud.fill",
    "cloud.sun.fill",
    "cloud.sun.fill",
    "cloud.fill",
    "cloud.fill",
    "cloud.moon.fill",
    "cloud.fill",
    "cloud.fill",
    "cloud.fill",
    "cloud.fill",
    "cloud.sun.fill",
    "cloud.sun.fill",
    "cloud.moon.fill",
    "moon.fill",
    "moon.fill",
    "cloud.moon.fill",
    "cloud.moon.fill",
    "cloud.sun.fill",
    "cloud.sun.fill",
    "cloud.fill",
    "cloud.moon.fill"
  ],
  "current_temperature": 7,
  "temperature": [
    8,
    9,
    12,
    12,
    13,
    11,
    8,
    7,
    8,
    8,
    11,
    11,
    11,
    10,
    8,
    8,
    11,
    11,
    11,
    12,
    12,
    12,
    11,
    11,
    11,
    10,
    9,
    10,
    10,
    11,
    11,
    11,
    11,
    10,
    10,
    11,
    13,
    13,
    12,
    12,
    11,
    11,
    11,
    12,
    12,
    12,
    11,
    11,
    11,
    11,
    12,
    13,
    13,
    13,
    13,
    13,
    13,
    13,
    13,
    13,
    14,
    14,
    13,
    13,
    13,
    13,
    14,
    14,
    15,
    15,
    14,
    14,
    13,
    11,
    10,
    9,
    10,
    11,
    10
  ]
}