{
  "spot": "Mallorca / Can Pastilla",
  "coordinates": {
    "latitude": 39.534,
    "longitude": 2.7191
  },
  "country_code": "ES",
  "is_weather_station": false,
  "month": [
    1,
    1,
    1,
    1,
    1,
    1,
    1,
    1,
    1,
    1,
    1,
    1,
    1,
    1,
    1,
    1,
    1,
    1,
    1,
    1,
    1,
    1,
    1,
    1,
    1,
    1,
    1,
    1,
    1,
    1,
    1,
    1,
    1,
    1,
    1,
    1,
    1,
    1,
    1,
    1,
    1,
    1,
    1,
    1,
    1,
    1,
    1,
    1,
    1,
    1,
    1,
    1,
    1,
    1,
    1,
    1,
    1,
    1,
    1,
    1,
    1,
    1,
    1,
    1,
    1,
    1,
    1,
    1,
    1,
    1,
    1,
    1,
    1,
    1,
    1,
    1,
    1,
    1,
    1,
    1
  ],
  "day": [
    15,
    15,
    15,
    15,
    15,
    15,
    15,
    15,
    16,
    16,
    16,
    16,
    16,
    16,
    16,
    16,
    17,
    17,
    17,
    17,
    17,
    17,
    17,
    17,
    18,
    18,
    18,
    18,
    18,
    18,
    18,
    18,
    19,
    19,
    19,
    19,
    19,
    19,
    19,
    19,
    20,
    20,
    20,
    20,
    20,
    20,
    20,
    20,
    21,
    21,
    21,
    21,
    21,
    21,
    21,
    21,
    22,
    22,
    22,
    22,
    22,
    22,
    22,
    22,
    23,
    23,
    23,
    23,
    23,
    23,
    23,
    23,
    24,
    24,
    24,
    24,
    24,
    24,
    24,
    24
  ],
  "weekday": [
    "Friday",
    "Friday",
    "Friday",
    "Friday",
    "Friday",
    "Friday",
    "Friday",
    "Friday",
    "Saturday",
    "Saturday",
    "Saturday",
    "Saturday",
    "Saturday",
    "Saturday",
    "Saturday",
    "Saturday",
    "Sunday",
    "Sunday",
    "Sunday",
    "Sunday",
    "Sunday",
    "Sunday",
    "Sunday",
    "Sunday",
    "Monday",
    "Monday",
    "Monday",
    "Monday",
    "Monday",
    "Monday",
    "Monday",
    "Monday",
    "Tuesday",
    "Tuesday",
    "Tuesday",
    "Tuesday",
    "Tuesday",
    "Tuesday",
    "Tuesday",
    "Tuesday",
    "Wednesday",
    "Wednesday",
    "Wednesday",
    "Wednesday",
    "Wednesday",
    "Wednesday",
    "Wednesday",
    "Wednesday",
    "Thursday",
    "Thursday",
    "Thursday",
    "Thursday",
    "Thursday",
    "Thursday",
    "Thursday",
    "Thursday",
    "Friday",
    "Friday",
    "Friday",
    "Friday",
    "Friday",
    "Friday",
    "Friday",
    "Friday",
    "Saturday",
    "Saturday",
    "Saturday",
    "Saturday",
    "Saturday",
    "Saturday",
    "Saturday",
    "Saturday",
    "Sunday",
    "Sunday",
    "Sunday",
    "Sunday",
    "Sunday",
    "Sunday",
    "Sunday",
    "Sunday"
  ],
  "hour": [
    6,
    8,
    10,
    12,
    14,
    16,
    18,
    20,
    6,
    8,
    10,
    12,
    14,
    16,
    18,
    20,
    1,
    4,
    7,
    10,
    13,
    16,
    19,
    22,
    1,
    4,
    7,
    10,
    13,
    16,
    19,
    22,
    1,
    4,
    7,
    10,
    13,
    16,
    19,
    22,
    1,
    4,
    7,
    10,
    13,
    16,
    19,
    22,
    1,
    4,
    7,
    10,
    13,
    16,
    19,
    22,
    1,
    4,
    7,
    10,
    13,
    16,
    19,
    22,
    1,
    4,
    7,
    10,
    13,
    16,
    19,
    22,
    1,
    4,
    7,
    10,
    13,
    16,
    19,
    22
  ],
  "current_wind": 8,
  "current_wind_direction": 318,
  "wind_speed": [
    6,
    6,
    11,
    14,
    15,
    11,
    6,
    6,
    9,
    6,
    14,
    14,
    12,
    8,
    5,
    3,
    6,
    7,
    8,
    7,
    11,
    8,
    5,
    5,
    3,
    2,
    8,
    5,
    3,
    6,
    3,
    3,
    2,
    2,
    3,
    3,
    9,
    9,
    6,
    6,
    6,
    6,
    5,
    5,
    9,
    9,
    6,
    6,
    8,
    5,
    5,
    6,
    10,
    9,
    9,
    13,
    14,
    11,
    16,
    13,
    17,
    23,
    20,
    17,
    18,
    17,
    17,
    21,
    4,
    23,
    15,
    13,
    18,
    19,
    17,
    18,
    21,
    17,
    12,
    10
  ],
  "wind_gusts": [
    8,
    14,
    14,
    17,
    18,
    18,
    12,
    9,
    15,
    17,
    21,
    20,
    18,
    13,
    10,
    3,
    7,
    10,
    10,
    10,
    15,
    12,
    7,
    6,
    4,
    3,
    11,
    8,
    6,
    9,
    4,
    4,
    3,
    2,
    3,
    4,
    10,
    11,
    8,
    9,
    8,
    8,
    7,
    9,
    14,
    15,
    8,
    8,
    13,
    7,
    7,
    9,
    13,
    11,
    13,
    24,
    27,
    22,
    27,
    23,
    26,
    32,
    32,
    28,
    28,
    27,
    27,
    26,
    5,
    28,
    25,
    22,
    29,
    30,
    28,
    28,
    28,
    25,
    20,
    16
  ],
  "wind_direction": [
    307,
    338,
    343,
    316,
    312,
    324,
    336,
    49,
    58,
    50,
    29,
    21,
    29,
    29,
    52,
    32,
    286,
    270,
    267,
    272,
    261,
    264,
    289,
    294,
    347,
    293,
    318,
    5,
    34,
    277,
    197,
    135,
    190,
    336,
    28,
    87,
    183,
    193,
    187,
    191,
    186,
    188,
    196,
    199,
    200,
    214,
    215,
    221,
    231,
    253,
    228,
    259,
    232,
    213,
    229,
    231,
    241,
    239,
    225,
    257,
    259,
    256,
    269,
    286,
    288,
    286,
    293,
    304,
    273,
    304,
    314,
    324,
    314,
    305,
    304,
    307,
    314,
    302,
    268,
    269
  ],
  "wave_height": [
    0.1,
    0.1,
    0.1,
    0.1,
    0.1,
    0.1,
    0.1,
    0.1,
    0.1,
    0.1,
    0.1,
    0.1,
    0.1,
    0.1,
    0.1,
    0.1,
    0.6,
    0.6,
    0.6,
    0.6,
    0.6,
    0.7,
    0.6,
    0.0,
    0,
    0,
    0,
    0,
    0,
    0,
    0,
    0,
    0,
    0,
    0,
    0,
    0,
    0,
    0,
    0,
    0,
    0,
    0,
    0,
    0,
    0,
    0,
    0,
    0,
    0,
    0,
    0,
    0,
    0,
    0,
    0,
    0,
    0,
    0,
    0,
    0,
    0,
    0,
    0,
    0,
    0,
    0,
    0,
    0,
    0,
    0,
    0,
    0,
    0,
    0,
    0,
    0,
    0,
    0,
    0
  ],
  "wave_period": [
    5.0,
    5.0,
    6.0,
    6.0,
    6.0,
    6.0,
    7.0,
    7.0,
    7.0,
    7.0,
    7.0,
    7.0,
    7.0,
    7.0,
    6.0,
    6.0,
    5.0,
    5.0,
    5.0,
    6.0,
    6.0,
    6.0,
    6.0,
    0.0,
    0,
    0,
    0,
    0,
    0,
    0,
    0,
    0,
    0,
    0,
    0,
    0,
    0,
    0,
    0,
    0,
    0,
    0,
    0,
    0,
    0,
    0,
    0,
    0,
    0,
    0,
    0,
    0,
    0,
    0,
    0,
    0,
    0,
    0,
    0,
    0,
    0,
    0,
    0,
    0,
    0,
    0,
    0,
    0,
    0,
    0,
    0,
    0,
    0,
    0,
    0,
    0,
    0,
    0,
    0,
    0
  ],
  "wave_direction": [
    209,
    210,
    210,
    215,
    216,
    216,
    217,
    218,
    220,
    219,
    217,
    217,
    216,
    215,
    218,
    218,
    218,
    217,
    217,
    216,
    215,
    213,
    213,
    0,
    0,
    0,
    0,
    0,
    0,
    0,
    0,
    0,
    0,
    0,
    0,
    0,
    0,
    0,
    0,
    0,
    0,
    0,
    0,
    0,
    0,
    0,
    0,
    0,
    0,
    0,
    0,
    0,
    0,
    0,
    0,
    0,
    0,
    0,
    0,
    0,
    0,
    0,
    0,
    0,
    0,
    0,
    0,
    0,
    0,
    0,
    0,
    0,
    0,
    0,
    0,
    0,
    0,
    0,
    0,
    0
  ],
  "weather_icon": [
    "moon.fill",
    "moon.fill",
    "sun.max.fill",
    "sun.max.fill",
    "cloud.sun.fill",
    "cloud.sun.fill",
    "moon.fill",
    "moon.fill",
    "cloud.moon.fill",
    "cloud.moon.fill",
    "sun.max.fill",
    "sun.max.fill",
    "sun.max.fill",
    "sun.max.fill",
    "moon.fill",
    "moon.fill",
    "moon.fill",
    "moon.fill",
    "moon.fill",
    "sun.max.fill",
    "sun.max.fill",
    "sun.max.fill",
    "moon.fill",
    "moon.fill",
    "moon.fill",
    "moon.fill",
    "moon.fill",
    "sun.max.fill",
    "sun.max.fill",
    "sun.max.fill",
    "moon.fill",
    "moon.fill",
    "moon.fill",
    "moon.fill",
    "moon.fill",
    "sun.max.fill",
    "sun.max.fill",
    "sun.max.fill",
    "moon.fill",
    "moon.fill",
    "cloud.moon.fill",
    "cloud.fill",
    "cloud.fill",
    "cloud.fill",
    "cloud.fill",
    "cloud.fill",
    "cloud.fill",
    "cloud.fill",
    "cloud.fill",
    "cloud.fill",
    "cloud.fill",
    "cloud.sun.fill",
    "sun.max.fill",
    "sun.max.fill",
    "moon.fill",
    "cloud.moon.fill",
    "cloud.moon.fill",
    "cloud.moon.fill",
    "cloud.moon.fill",
    "cloud.drizzle.fill",
    "cloud.rain.fill",
    "cloud.sun.rain.fill",
    "moon.fill",
    "cloud.moon.fill",
    "cloud.moon.fill",
    "cloud.moon.fill",
    "moon.fill",
    "cloud.sun.fill",
    "cloud.drizzle.fill",
    "cloud.sun.rain.fill",
    "cloud.moon.fill",
    "cloud.moon.fill",
    "moon.fill",
    "moon.fill",
    "cloud.moon.fill",
    "cloud.fill",
    "cloud.fill",
    "cloud.sun.fill",
    "cloud.fill",
    "cloud.moon.fill"
  ],
  "current_temperature": 7,
  "temperature": [
    6,
    6,
    11,
    12,
    12,
    12,
    8,
    8,
    8,
    6,
    10,
    11,
    12,
    10,
    6,
    6,
    8,
    9,
    10,
    12,
    15,
    14,
    10,
    10,
    9,
    9,
    10,
    12,
    16,
    15,
    11,
    10,
    10,
    10,
    9,
    12,
    15,
    15,
    12,
    12,
    12,
    12,
    12,
    14,
    16,
    16,
    12,
    12,
    12,
    12,
    12,
    14,
    16,
    15,
    13,
    14,
    14,
    13,
    14,
    13,
    13,
    15,
    14,
    13,
    11,
    11,
    10,
    10,
    10,
    11,
    9,
    8,
    8,
    8,
    9,
    10,
    11,
    12,
    11,
    11
  ]
}