{
  "spot": "Noordwijk",
  "coordinates": {
    "latitude": 52.27,
    "longitude": 4.3
  },
  "country_code": "NL",
  "is_weather_station": false,
  "month": [
    1,
    1,
    1,
    1,
    1,
    1,
    1,
    1,
    1,
    1,
    1,
    1,
    1,
    1,
    1,
    1,
    1,
    1,
    1,
    1,
    1,
    1,
    1,
    1,
    1,
    1,
    1,
    1,
    1,
    1,
    1,
    1,
    1,
    1,
    1,
    1,
    1,
    1,
    1,
    1,
    1,
    1,
    1,
    1,
    1,
    1,
    1,
    1,
    1,
    1,
    1,
    1,
    1,
    1,
    1,
    1,
    1,
    1,
    1,
    1,
    1,
    1,
    1,
    1,
    1,
    1,
    1,
    1,
    1,
    1,
    1,
    1,
    1,
    1,
    1,
    1,
    1,
    1,
    1,
    1
  ],
  "day": [
    14,
    14,
    14,
    14,
    14,
    14,
    14,
    14,
    15,
    15,
    15,
    15,
    15,
    15,
    15,
    15,
    16,
    16,
    16,
    16,
    16,
    16,
    16,
    16,
    17,
    17,
    17,
    17,
    17,
    17,
    17,
    17,
    18,
    18,
    18,
    18,
    18,
    18,
    18,
    18,
    19,
    19,
    19,
    19,
    19,
    19,
    19,
    19,
    20,
    20,
    20,
    20,
    20,
    20,
    20,
    20,
    21,
    21,
    21,
    21,
    21,
    21,
    21,
    21,
    22,
    22,
    22,
    22,
    22,
    22,
    22,
    22,
    23,
    23,
    23,
    23,
    23,
    23,
    23,
    23
  ],
  "weekday": [
    "Thursday",
    "Thursday",
    "Thursday",
    "Thursday",
    "Thursday",
    "Thursday",
    "Thursday",
    "Thursday",
    "Friday",
    "Friday",
    "Friday",
    "Friday",
    "Friday",
    "Friday",
    "Friday",
    "Friday",
    "Saturday",
    "Saturday",
    "Saturday",
    "Saturday",
    "Saturday",
    "Saturday",
    "Saturday",
    "Saturday",
    "Sunday",
    "Sunday",
    "Sunday",
    "Sunday",
    "Sunday",
    "Sunday",
    "Sunday",
    "Sunday",
    "Monday",
    "Monday",
    "Monday",
    "Monday",
    "Monday",
    "Monday",
    "Monday",
    "Monday",
    "Tuesday",
    "Tuesday",
    "Tuesday",
    "Tuesday",
    "Tuesday",
    "Tuesday",
    "Tuesday",
    "Tuesday",
    "Wednesday",
    "Wednesday",
    "Wednesday",
    "Wednesday",
    "Wednesday",
    "Wednesday",
    "Wednesday",
    "Wednesday",
    "Thursday",
    "Thursday",
    "Thursday",
    "Thursday",
    "Thursday",
    "Thursday",
    "Thursday",
    "Thursday",
    "Friday",
    "Friday",
    "Friday",
    "Friday",
    "Friday",
    "Friday",
    "Friday",
    "Friday",
    "Saturday",
    "Saturday",
    "Saturday",
    "Saturday",
    "Saturday",
    "Saturday",
    "Saturday",
    "Saturday"
  ],
  "hour": [
    6,
    8,
    10,
    12,
    14,
    16,
    18,
    20,
    6,
    8,
    10,
    12,
    14,
    16,
    18,
    20,
    1,
    4,
    7,
    10,
    13,
    16,
    19,
    22,
    1,
    4,
    7,
    10,
    13,
    16,
    19,
    22,
    1,
    4,
    7,
    10,
    13,
    16,
    19,
    22,
    1,
    4,
    7,
    10,
    13,
    16,
    19,
    22,
    1,
    4,
    7,
    10,
    13,
    16,
    19,
    22,
    1,
    4,
    7,
    10,
    13,
    16,
    19,
    22,
    1,
    4,
    7,
    10,
    13,
    16,
    19,
    22,
    1,
    4,
    7,
    10,
    13,
    16,
    19,
    22
  ],
  "current_wind": 9,
  "current_wind_direction": 93,
  "wind_speed": [
    9,
    11,
    13,
    14,
    12,
    14,
    16,
    15,
    12,
    8,
    3,
    2,
    2,
    5,
    9,
    8,
    7,
    7,
    7,
    13,
    14,
    15,
    16,
    15,
    16,
    13,
    9,
    7,
    2,
    19,
    15,
    16,
    15,
    13,
    13,
    13,
    15,
    15,
    14,
    13,
    13,
    16,
    21,
    20,
    21,
    18,
    21,
    23,
    26,
    25,
    26,
    26,
    24,
    21,
    18,
    16,
    19,
    22,
    25,
    28,
    24,
    22,
    24,
    22,
    21,
    18,
    14,
    21,
    19,
    15,
    13,
    11,
    15,
    12,
    35,
    30,
    28,
    27,
    26,
    24
  ],
  "wind_gusts": [
    13,
    14,
    14,
    17,
    16,
    18,
    18,
    18,
    18,
    14,
    6,
    4,
    6,
    8,
    9,
    8,
    7,
    8,
    7,
    14,
    16,
    17,
    19,
    19,
    21,
    16,
    10,
    7,
    2,
    25,
    22,
    21,
    19,
    17,
    15,
    17,
    19,
    19,
    19,
    18,
    18,
    21,
    24,
    24,
    25,
    24,
    29,
    34,
    38,
    37,
    41,
    43,
    39,
    26,
    22,
    20,
    22,
    25,
    29,
    33,
    28,
    27,
    29,
    28,
    26,
    24,
    21,
    26,
    24,
    21,
    18,
    15,
    23,
    19,
    40,
    37,
    33,
    31,
    30,
    28
  ],
  "wind_direction": [
    62,
    96,
    105,
    111,
    103,
    98,
    85,
    81,
    47,
    71,
    107,
    158,
    172,
    293,
    29,
    53,
    159,
    191,
    160,
    193,
    189,
    184,
    166,
    155,
    143,
    138,
    133,
    124,
    163,
    342,
    331,
    318,
    307,
    299,
    287,
    272,
    263,
    263,
    261,
    255,
    247,
    219,
    215,
    206,
    205,
    185,
    184,
    190,
    194,
    195,
    195,
    197,
    213,
    310,
    270,
    310,
    281,
    263,
    264,
    270,
    271,
    262,
    259,
    261,
    256,
    248,
    235,
    217,
    200,
    171,
    144,
    140,
    237,
    234,
    355,
    338,
    326,
    315,
    306,
    307
  ],
  "wave_height": [
    1.1,
    1.0,
    0.9,
    0.9,
    0.8,
    0.8,
    0.8,
    0.8,
    0.6,
    0.5,
    0.5,
    0.5,
    0.4,
    0.4,
    0.4,
    0.4,
    0.3,
    0.3,
    0.3,
    0.4,
    0.4,
    0.5,
    0.5,
    0.0,
    0.6,
    0.7,
    0.7,
    0.6,
    0.6,
    0.6,
    0.8,
    0.8,
    0.8,
    0.7,
    0.7,
    0.7,
    0.7,
    0.8,
    0.8,
    0.8,
    0.8,
    0.9,
    0.9,
    0.9,
    1.0,
    1.0,
    1.0,
    1.1,
    1.1,
    1.1,
    1.2,
    1.2,
    1.3,
    1.2,
    1.2,
    1.2,
    1.2,
    1.2,
    1.3,
    1.3,
    1.4,
    1.4,
    1.4,
    1.5,
    1.5,
    1.6,
    1.6,
    1.6,
    1.6,
    1.5,
    1.5,
    1.5,
    1.5,
    1.5,
    1.5,
    1.5,
    1.4,
    1.4,
    1.4,
    0
  ],
  "wave_period": [
    8.0,
    8.0,
    9.0,
    9.0,
    9.0,
    9.0,
    8.0,
    8.0,
    7.0,
    7.0,
    7.0,
    7.0,
    7.0,
    7.0,
    6.0,
    6.0,
    5.0,
    5.0,
    5.0,
    4.0,
    4.0,
    4.0,
    4.0,
    0.0,
    5,
    5,
    5,
    5,
    5,
    5,
    6,
    6,
    6,
    7,
    6,
    6,
    6,
    6,
    5,
    6,
    5,
    5,
    6,
    6,
    6,
    6,
    6,
    6,
    6,
    6,
    6,
    6,
    6,
    6,
    7,
    7,
    7,
    7,
    7,
    7,
    7,
    7,
    7,
    7,
    7,
    7,
    7,
    7,
    7,
    7,
    7,
    7,
    7,
    7,
    7,
    7,
    7,
    7,
    7,
    0
  ],
  "wave_direction": [
    347,
    348,
    349,
    350,
    350,
    351,
    346,
    340,
    351,
    355,
    356,
    357,
    357,
    357,
    357,
    349,
    187,
    143,
    111,
    139,
    157,
    164,
    193,
    0,
    234,
    233,
    244,
    246,
    248,
    260,
    280,
    289,
    293,
    307,
    306,
    312,
    311,
    309,
    303,
    305,
    290,
    282,
    277,
    271,
    264,
    251,
    251,
    253,
    246,
    246,
    244,
    253,
    257,
    257,
    261,
    266,
    273,
    275,
    269,
    280,
    283,
    282,
    284,
    285,
    286,
    294,
    296,
    295,
    295,
    297,
    291,
    292,
    292,
    305,
    307,
    310,
    310,
    307,
    311,
    0
  ],
  "weather_icon": [
    "cloud.fill",
    "cloud.fill",
    "cloud.fill",
    "cloud.fill",
    "cloud.fill",
    "cloud.fill",
    "cloud.moon.fill",
    "cloud.fill",
    "cloud.fill",
    "cloud.fill",
    "sun.max.fill",
    "cloud.sun.fill",
    "cloud.sun.fill",
    "cloud.sun.fill",
    "cloud.moon.rain.fill",
    "cloud.moon.fill",
    "cloud.fill",
    "cloud.fill",
    "cloud.fill",
    "cloud.fill",
    "cloud.fill",
    "cloud.fill",
    "cloud.fill",
    "cloud.snow.fill",
    "cloud.snow.fill",
    "cloud.snow.fill",
    "cloud.snow.fill",
    "cloud.sleet.fill",
    "cloud.drizzle.fill",
    "cloud.drizzle.fill",
    "cloud.fill",
    "cloud.moon.fill",
    "moon.fill",
    "moon.fill",
    "cloud.moon.fill",
    "cloud.sun.fill",
    "cloud.fill",
    "cloud.sun.fill",
    "cloud.moon.fill",
    "moon.fill",
    "cloud.moon.fill",
    "cloud.fill",
    "cloud.drizzle.fill",
    "cloud.fill",
    "cloud.fill",
    "cloud.drizzle.fill",
    "cloud.fill",
    "cloud.rain.fill",
    "cloud.drizzle.fill",
    "cloud.drizzle.fill",
    "cloud.rain.fill",
    "cloud.drizzle.fill",
    "cloud.rain.fill",
    "cloud.heavyrain.fill",
    "cloud.drizzle.fill",
    "cloud.drizzle.fill",
    "cloud.moon.fill",
    "cloud.moon.fill",
    "cloud.fill",
    "cloud.fill",
    "cloud.fill",
    "cloud.sun.fill",
    "cloud.moon.fill",
    "cloud.fill",
    "cloud.fill",
    "cloud.fill",
    "cloud.fill",
    "cloud.rain.fill",
    "cloud.drizzle.fill",
    "cloud.drizzle.fill",
    "cloud.rain.fill",
    "cloud.heavyrain.fill",
    "cloud.drizzle.fill",
    "cloud.fill",
    "cloud.rain.fill",
    "cloud.snow.fill",
    "cloud.snow.fill",
    "cloud.snow.fill",
    "cloud.snow.fill",
    "cloud.snow.fill"
  ],
  "current_temperature": 4,
  "temperature": [
    4,
    4,
    3,
    2,
    2,
    2,
    2,
    0,
    -1,
    0,
    1,
    1,
    2,
    3,
    3,
    2,
    2,
    2,
    2,
    2,
    2,
    2,
    1,
    0,
    0,
    1,
    0,
    1,
    1,
    6,
    6,
    6,
    6,
    6,
    6,
    6,
    6,
    6,
    6,
    6,
    6,
    6,
    5,
    4,
    3,
    3,
    4,
    5,
    6,
    6,
    7,
    8,
    8,
    7,
    6,
    4,
    5,
    5,
    6,
    6,
    6,
    6,
    6,
    6,
    6,
    6,
    6,
    5,
    5,
    4,
    5,
    5,
    7,
    7,
    4,
    4,
    5,
    4,
    3,
    4
  ]
}