{
  "spot": "Tarifa Centro",
  "coordinates": {
    "latitude": 36.0144,
    "longitude": -5.5997
  },
  "country_code": "ES",
  "is_weather_station": false,
  "month": [
    12,
    12,
    12,
    12,
    12,
    12,
    12,
    12,
    1,
    1,
    1,
    1,
    1,
    1,
    1,
    1,
    1,
    1,
    1,
    1,
    1,
    1,
    1,
    1,
    1,
    1,
    1,
    1,
    1,
    1,
    1,
    1,
    1,
    1,
    1,
    1,
    1,
    1,
    1,
    1,
    1,
    1,
    1,
    1,
    1,
    1,
    1,
    1,
    1,
    1,
    1,
    1,
    1,
    1,
    1,
    1,
    1,
    1,
    1,
    1,
    1,
    1,
    1,
    1,
    1,
    1,
    1,
    1,
    1,
    1,
    1,
    1,
    1,
    1,
    1,
    1,
    1,
    1,
    1,
    1
  ],
  "day": [
    31,
    31,
    31,
    31,
    31,
    31,
    31,
    31,
    1,
    1,
    1,
    1,
    1,
    1,
    1,
    1,
    2,
    2,
    2,
    2,
    2,
    2,
    2,
    2,
    3,
    3,
    3,
    3,
    3,
    3,
    3,
    3,
    4,
    4,
    4,
    4,
    4,
    4,
    4,
    4,
    5,
    5,
    5,
    5,
    5,
    5,
    5,
    5,
    6,
    6,
    6,
    6,
    6,
    6,
    6,
    6,
    7,
    7,
    7,
    7,
    7,
    7,
    7,
    7,
    8,
    8,
    8,
    8,
    8,
    8,
    8,
    8,
    9,
    9,
    9,
    9,
    9,
    9,
    9,
    9
  ],
  "weekday": [
    "Thursday",
    "Thursday",
    "Thursday",
    "Thursday",
    "Thursday",
    "Thursday",
    "Thursday",
    "Thursday",
    "Friday",
    "Friday",
    "Friday",
    "Friday",
    "Friday",
    "Friday",
    "Friday",
    "Friday",
    "Saturday",
    "Saturday",
    "Saturday",
    "Saturday",
    "Saturday",
    "Saturday",
    "Saturday",
    "Saturday",
    "Sunday",
    "Sunday",
    "Sunday",
    "Sunday",
    "Sunday",
    "Sunday",
    "Sunday",
    "Sunday",
    "Monday",
    "Monday",
    "Monday",
    "Monday",
    "Monday",
    "Monday",
    "Monday",
    "Monday",
    "Tuesday",
    "Tuesday",
    "Tuesday",
    "Tuesday",
    "Tuesday",
    "Tuesday",
    "Tuesday",
    "Tuesday",
    "Wednesday",
    "Wednesday",
    "Wednesday",
    "Wednesday",
    "Wednesday",
    "Wednesday",
    "Wednesday",
    "Wednesday",
    "Thursday",
    "Thursday",
    "Thursday",
    "Thursday",
    "Thursday",
    "Thursday",
    "Thursday",
    "Thursday",
    "Friday",
    "Friday",
    "Friday",
    "Friday",
    "Friday",
    "Friday",
    "Friday",
    "Friday",
    "Saturday",
    "Saturday",
    "Saturday",
    "Saturday",
    "Saturday",
    "Saturday",
    "Saturday",
    "Saturday"
  ],
  "hour": [
    6,
    8,
    10,
    12,
    14,
    16,
    18,
    20,
    6,
    8,
    10,
    12,
    14,
    16,
    18,
    20,
    6,
    8,
    10,
    12,
    14,
    16,
    18,
    20,
    1,
    4,
    7,
    10,
    13,
    16,
    19,
    22,
    1,
    4,
    7,
    10,
    13,
    16,
    19,
    22,
    1,
    4,
    7,
    10,
    13,
    16,
    19,
    22,
    1,
    4,
    7,
    10,
    13,
    16,
    19,
    22,
    1,
    4,
    7,
    10,
    13,
    16,
    19,
    22,
    1,
    4,
    7,
    10,
    13,
    16,
    19,
    22,
    1,
    4,
    7,
    10,
    13,
    16,
    19,
    22
  ],
  "current_wind": 12,
  "current_wind_direction": 259,
  "wind_speed": [
    8.0,
    8.0,
    9.0,
    12.0,
    14.0,
    13.0,
    11.0,
    11.0,
    22.0,
    18.0,
    16.0,
    17.0,
    17.0,
    18.0,
    14.0,
    18.0,
    14.0,
    12.0,
    10.0,
    10.0,
    11.0,
    12.0,
    10.0,
    10.0,
    8,
    8,
    7,
    7,
    9,
    11,
    10,
    8,
    6,
    5,
    5,
    7,
    7,
    9,
    8,
    5,
    3,
    4,
    9,
    4,
    3,
    3,
    4,
    5,
    4,
    4,
    4,
    5,
    7,
    9,
    7,
    9,
    15,
    23,
    19,
    13,
    4,
    5,
    8,
    8,
    8,
    9,
    7,
    7,
    9,
    14,
    14,
    15,
    15,
    12,
    12,
    16,
    21,
    26,
    23,
    19
  ],
  "wind_gusts": [
    8.0,
    8.0,
    12.0,
    15.0,
    16.0,
    16.0,
    17.0,
    18.0,
    32.0,
    28.0,
    24.0,
    24.0,
    22.0,
    21.0,
    20.0,
    22.0,
    24.0,
    18.0,
    16.0,
    16.0,
    15.0,
    14.0,
    14.0,
    15.0,
    11,
    10,
    9,
    9,
    12,
    14,
    13,
    11,
    10,
    7,
    8,
    10,
    10,
    11,
    10,
    7,
    7,
    8,
    12,
    5,
    4,
    4,
    5,
    6,
    4,
    4,
    4,
    6,
    9,
    10,
    9,
    12,
    21,
    29,
    26,
    17,
    4,
    5,
    9,
    11,
    11,
    12,
    12,
    11,
    14,
    18,
    19,
    20,
    21,
    17,
    18,
    23,
    29,
    34,
    30,
    27
  ],
  "wind_direction": [
    7,
    352,
    348,
    324,
    302,
    307,
    300,
    307,
    322,
    318,
    321,
    310,
    303,
    290,
    291,
    314,
    329,
    328,
    328,
    303,
    290,
    287,
    303,
    320,
    305,
    301,
    292,
    290,
    277,
    276,
    288,
    306,
    294,
    294,
    269,
    291,
    273,
    277,
    292,
    307,
    271,
    243,
    228,
    277,
    331,
    259,
    275,
    311,
    359,
    26,
    35,
    33,
    49,
    72,
    90,
    74,
    79,
    52,
    46,
    42,
    113,
    198,
    296,
    297,
    301,
    301,
    286,
    260,
    266,
    263,
    262,
    259,
    268,
    269,
    256,
    274,
    271,
    270,
    280,
    288
  ],
  "wave_height": [
    0.0,
    0.0,
    0.0,
    0.0,
    0.0,
    0.0,
    0.0,
    0.0,
    0.0,
    0.0,
    0.0,
    0.0,
    0.0,
    0.0,
    0.0,
    0.0,
    0.0,
    0.0,
    0.0,
    0.0,
    0.0,
    0.0,
    0.0,
    0.0,
    0,
    0,
    0,
    0,
    0,
    0,
    0,
    0,
    0,
    0,
    0,
    0,
    0,
    0,
    0,
    0,
    0,
    0,
    0,
    0,
    0,
    0,
    0,
    0,
    0,
    0,
    0,
    0,
    0,
    0,
    0,
    0,
    0,
    0,
    0,
    0,
    0,
    0,
    0,
    0,
    0,
    0,
    0,
    0,
    0,
    0,
    0,
    0,
    0,
    0,
    0,
    0,
    0,
    0,
    0,
    0
  ],
  "wave_period": [
    0.0,
    0.0,
    0.0,
    0.0,
    0.0,
    0.0,
    0.0,
    0.0,
    0.0,
    0.0,
    0.0,
    0.0,
    0.0,
    0.0,
    0.0,
    0.0,
    0.0,
    0.0,
    0.0,
    0.0,
    0.0,
    0.0,
    0.0,
    0.0,
    0,
    0,
    0,
    0,
    0,
    0,
    0,
    0,
    0,
    0,
    0,
    0,
    0,
    0,
    0,
    0,
    0,
    0,
    0,
    0,
    0,
    0,
    0,
    0,
    0,
    0,
    0,
    0,
    0,
    0,
    0,
    0,
    0,
    0,
    0,
    0,
    0,
    0,
    0,
    0,
    0,
    0,
    0,
    0,
    0,
    0,
    0,
    0,
    0,
    0,
    0,
    0,
    0,
    0,
    0,
    0
  ],
  "wave_direction": [
    0,
    0,
    0,
    0,
    0,
    0,
    0,
    0,
    0,
    0,
    0,
    0,
    0,
    0,
    0,
    0,
    0,
    0,
    0,
    0,
    0,
    0,
    0,
    0,
    0,
    0,
    0,
    0,
    0,
    0,
    0,
    0,
    0,
    0,
    0,
    0,
    0,
    0,
    0,
    0,
    0,
    0,
    0,
    0,
    0,
    0,
    0,
    0,
    0,
    0,
    0,
    0,
    0,
    0,
    0,
    0,
    0,
    0,
    0,
    0,
    0,
    0,
    0,
    0,
    0,
    0,
    0,
    0,
    0,
    0,
    0,
    0,
    0,
    0,
    0,
    0,
    0,
    0,
    0,
    0
  ],
  "weather_icon": [
    "moon.fill",
    "moon.fill",
    "sun.max.fill",
    "sun.max.fill",
    "sun.max.fill",
    "sun.max.fill",
    "sun.max.fill",
    "moon.fill",
    "cloud.moon.fill",
    "moon.fill",
    "sun.max.fill",
    "sun.max.fill",
    "sun.max.fill",
    "sun.max.fill",
    "sun.max.fill",
    "cloud.moon.rain.fill",
    "moon.fill",
    "moon.fill",
    "sun.max.fill",
    "sun.max.fill",
    "sun.max.fill",
    "sun.max.fill",
    "sun.max.fill",
    "moon.fill",
    "moon.fill",
    "moon.fill",
    "moon.fill",
    "sun.max.fill",
    "sun.max.fill",
    "sun.max.fill",
    "moon.fill",
    "moon.fill",
    "moon.fill",
    "cloud.moon.fill",
    "cloud.moon.fill",
    "cloud.sun.fill",
    "cloud.sun.fill",
    "sun.max.fill",
    "moon.fill",
    "moon.fill",
    "moon.fill",
    "cloud.moon.fill",
    "cloud.moon.fill",
    "cloud.drizzle.fill",
    "cloud.drizzle.fill",
    "cloud.fill",
    "cloud.fill",
    "cloud.fill",
    "cloud.fill",
    "cloud.fill",
    "cloud.moon.fill",
    "cloud.sun.fill",
    "cloud.fill",
    "cloud.fill",
    "cloud.fill",
    "cloud.fill",
    "cloud.drizzle.fill",
    "cloud.heavyrain.fill",
    "cloud.heavyrain.fill",
    "cloud.heavyrain.fill",
    "cloud.heavyrain.fill",
    "cloud.fill",
    "cloud.moon.fill",
    "moon.fill",
    "moon.fill",
    "moon.fill",
    "moon.fill",
    "sun.max.fill",
    "sun.max.fill",
    "sun.max.fill",
    "cloud.moon.fill",
    "cloud.moon.rain.fill",
    "cloud.moon.rain.fill",
    "cloud.moon.rain.fill",
    "cloud.moon.rain.fill",
    "cloud.sun.rain.fill",
    "sun.max.fill",
    "cloud.sun.rain.fill",
    "moon.fill",
    "cloud.drizzle.fill"
  ],
  "current_temperature": 12,
  "temperature": [
    7.0,
    6.0,
    10.0,
    12.0,
    13.0,
    13.0,
    10.0,
    11.0,
    10.0,
    10.0,
    10.0,
    12.0,
    12.0,
    12.0,
    11.0,
    10.0,
    6.0,
    6.0,
    8.0,
    10.0,
    10.0,
    11.0,
    8.0,
    8.0,
    9,
    8,
    8,
    9,
    12,
    12,
    10,
    9,
    9,
    9,
    9,
    9,
    11,
    11,
    10,
    9,
    9,
    9,
    10,
    9,
    9,
    10,
    10,
    9,
    8,
    8,
    8,
    9,
    12,
    12,
    11,
    11,
    11,
    10,
    9,
    9,
    9,
    10,
    7,
    7,
    7,
    7,
    7,
    8,
    11,
    13,
    12,
    12,
    12,
    12,
    12,
    13,
    15,
    15,
    14,
    14
  ]
}